sirtuin/main.py
sirtuin/controllers/aws_cloudfront.py
sirtuin/controllers/aws_container.py
sirtuin/controllers/http_headers.py
sirtuin/models/aws_cloudfront.py
sirtuin/models/aws_container.py
sirtuin/models/aws_instances.py
sirtuin/models/aws_regions.py
sirtuin/models/base_models.py
sirtuin/models/http_headers.py
sirtuin/utils/cleaners.py
sirtuin/utils/constants.py
sirtuin/utils/decorators.py
sirtuin/utils/dumpers.py
sirtuin/utils/filepaths.py
sirtuin/utils/loaders.py
sirtuin-1.3.0.dist-info/METADATA
sirtuin-1.3.0.dist-info/WHEEL
sirtuin-1.3.0.dist-info/entry_points.txt
sirtuin-1.3.0.dist-info/licenses/LICENSE
sirtuin-1.3.0.dist-info/RECORD
