Metadata-Version: 2.4
Name: sirtuin
Version: 1.3.0
Summary: AWS routines for Python projects
Project-URL: Homepage, https://github.com/merylldindin/sirtuin
Project-URL: Repository, https://github.com/merylldindin/sirtuin
Author-email: Meryll Dindin <merylldin@gmail.com>
License: Apache-2.0
License-File: LICENSE
Classifier: Development Status :: 4 - Beta
Classifier: Intended Audience :: Developers
Classifier: License :: OSI Approved :: Apache Software License
Classifier: Programming Language :: Python :: 3.13
Requires-Python: ==3.13.*
Requires-Dist: pydantic>=2.0
Requires-Dist: pyyaml>=6.0
Requires-Dist: tomli>=2.0
Requires-Dist: typer>=0.9
